<?xml version="1.0" encoding="UTF-8"  ?>
<mods:mods xmlns:mods="http://www.loc.gov/mods/v3" 
 xmlns:xlink="http://www.w3.org/1999/xlink" 
 xmlns="http://www.loc.gov/mods/v3" 
 xmlns:xsi="http://www.w3.org/2001/XMLSchema-instance" 
 xsi:schemaLocation="http://www.loc.gov/mods/v3 
 http://www.loc.gov/standards/mods/v3/mods-3-2.xsd" ID="MODS" version="3.2"><!-- Volunteer Voices MODS profile 
 released 14 December 2006 by Melanie Feltner-Reichert -->
<!-- Volunteer Voices Workbook 
 version 1.0 released 6 February 2007 by Christine Haygood Deane  -->
<!-- Content Contributor:  John Neal -->  
<!-- Project:  Volunteer Voices -->  
<!-- Record Creation Date:  Fri Feb 1 16:00:03 EST 2008 -->  
<!-- FILENAME: C:\Scan\00\xml\0082_000050_000220_0000.xml  -->  
<!-- NUMBER_OF_CONSTITUENT_FILES: 1: -->  
<!-- Reload: none --> 
<!-- PAGE VALIDATION :1:1:1:1:1:1:1: -->  
<mods:titleInfo>
<mods:title>Flood in Morristown, Tennessee</mods:title>
</mods:titleInfo>
<mods:name >
<mods:namePart>unknown</mods:namePart>
<mods:role>
<mods:roleTerm authority="marcrelator">Photographer</mods:roleTerm>
</mods:role>
</mods:name>
<mods:originInfo>
<mods:dateCreated qualifier="inferred" keyDate="yes"  encoding="w3cdtf">1963-07</mods:dateCreated>
</mods:originInfo>
<mods:language>
<mods:languageTerm type="code" authority="iso639-2b">eng</mods:languageTerm>
</mods:language>
<mods:typeOfResource>still image</mods:typeOfResource>
<mods:genre authority="aat" >black-and-white photograph</mods:genre>
<mods:physicalDescription>
<mods:digitalOrigin>reformatted digital</mods:digitalOrigin>
<mods:internetMediaType>image/jpeg</mods:internetMediaType>
<mods:extent>1 digital image; 1 photograph</mods:extent>
</mods:physicalDescription>
<mods:abstract> This photograph is titled, &#x0022;Flood in Morristown, Tennessee&#x0022;. Written on the reverse side, &#x0022;Morristown&#x0027;s Main St flood July 1963.  Rescue Squad boat in front of Princess Theaterr.  Turkey Creek at this  time had several channels that ran under the City.  When a sudden deluge hit all at once, Morristown Streets would flood.  Urban Renewal Projeects stopped the annual calamity in the late 1960s&#x0022;.</mods:abstract>
<mods:subject authority="lcsh">
<mods:geographic>Morristown (Tenn.)</mods:geographic>
<mods:geographic>Hamblen County (Tenn.)</mods:geographic>
<mods:name>
<mods:namePart>Morristown (Tenn.)</mods:namePart>
</mods:name>
<mods:name>
<mods:namePart>Princess Theater</mods:namePart>
</mods:name>
</mods:subject>
<mods:subject authority="vv">
<mods:temporal>A.9</mods:temporal>
<mods:topic>D.16</mods:topic>
<mods:geographic>C.32</mods:geographic>
</mods:subject>
<mods:relatedItem type="constituent">
<mods:identifier type="local">0082_000050_000220_0001</mods:identifier>
</mods:relatedItem >
<mods:identifier type="uri"></mods:identifier>
<mods:location>
<mods:physicalLocation type="repository">Hamblen County Archives</mods:physicalLocation>
<mods:physicalLocation type="city">Morristown</mods:physicalLocation>
<mods:physicalLocation type="state">Tennessee</mods:physicalLocation>
<mods:physicalLocation type="county">C.32</mods:physicalLocation>
<mods:physicalLocation type="collection">Hamblen County Archives</mods:physicalLocation>
<mods:url>Jody</mods:url>
</mods:location>
<mods:recordInfo>
<mods:recordContentSource>University of Tennessee Special Collections Library</mods:recordContentSource>
<mods:recordCreationDate encoding="w3cdtf">2008-02-01</mods:recordCreationDate>
<mods:languageOfCataloging>
<mods:languageTerm type="code" authority="iso639-2b">eng</mods:languageTerm>
</mods:languageOfCataloging>
</mods:recordInfo>
<mods:accessCondition type="useAndReproduction">http://idserver.utk.edu/?id=200600000001200</mods:accessCondition>
</mods:mods>


