<?xml version="1.0" encoding="UTF-8"  ?>
<mods:mods xmlns:mods="http://www.loc.gov/mods/v3" 
 xmlns:xlink="http://www.w3.org/1999/xlink" 
 xmlns="http://www.loc.gov/mods/v3" 
 xmlns:xsi="http://www.w3.org/2001/XMLSchema-instance" 
 xsi:schemaLocation="http://www.loc.gov/mods/v3 
 http://www.loc.gov/standards/mods/v3/mods-3-2.xsd" ID="MODS" version="3.2"><!-- Volunteer Voices MODS profile 
 released 14 December 2006 by Melanie Feltner-Reichert -->
<!-- Volunteer Voices Workbook 
 version 1.0 released 6 February 2007 by Christine Haygood Deane  -->
<!-- Content Contributor:  Chris Caldwell -->  
<!-- Project:  Volunteer Voices -->  
<!-- Record Creation Date:  Mon Aug 18 2008 13:57:18 GMT-0400 (EDT) -->  
<!-- FILENAME: C:\Scan\00\xml\0106_000054_000207_0000.xml  -->  
<!-- NUMBER_OF_CONSTITUENT_FILES: 1: -->  
<!-- Reload: none --> 
<!-- PAGE VALIDATION :1:1:1:1:1:1:1: -->  
<mods:titleInfo>
<mods:title>Confederate Twenty Dollar Bill</mods:title>
</mods:titleInfo>
<mods:name  type="corporate">
<mods:namePart>Confederate States of America</mods:namePart>
<mods:role>
<mods:roleTerm authority="marcrelator">Printer</mods:roleTerm>
</mods:role>
</mods:name>
<mods:originInfo>
<mods:dateCreated  keyDate="yes"  encoding="w3cdtf">1861-09-02</mods:dateCreated>
<mods:dateIssued  encoding="w3cdtf">1861</mods:dateIssued>
<mods:publisher>Confederate States of America</mods:publisher>
</mods:originInfo>
<mods:language>
<mods:languageTerm type="code" authority="iso639-2b">eng</mods:languageTerm>
</mods:language>
<mods:typeOfResource>text</mods:typeOfResource>
<mods:genre authority="marcgt" >realia</mods:genre>
<mods:physicalDescription>
<mods:digitalOrigin>reformatted digital</mods:digitalOrigin>
<mods:internetMediaType>image/jpeg</mods:internetMediaType>
<mods:extent>1 digital image; 1</mods:extent>
</mods:physicalDescription>
<mods:abstract>Bank note from Richmond, Virginia; Printed by Duncan, Richmond, Virginia; images of children and a bee hive, classical lady standing between a ship&#x0027;s anchor and cotton bales, with a palm tree in background. </mods:abstract>
<mods:subject authority="vv">
<mods:temporal>A.5</mods:temporal>
</mods:subject>\n<mods:subject>\n<mods:topic>Tennessee History</mods:topic>\n</mods:subject>
<mods:relatedItem type="constituent">
<mods:identifier type="local">0106_000054_000207_0001</mods:identifier>
</mods:relatedItem >
<mods:identifier type="uri"></mods:identifier>
<mods:location>
<mods:physicalLocation type="repository">Wilson County Archives</mods:physicalLocation>
<mods:physicalLocation type="city">Lebanon</mods:physicalLocation>
<mods:physicalLocation type="state">Tennessee</mods:physicalLocation>
<mods:physicalLocation type="county">C.95</mods:physicalLocation>
<mods:physicalLocation type="collection">Miscellaneous Collections</mods:physicalLocation>
<mods:url>Jody</mods:url>
</mods:location>
<mods:recordInfo>
<mods:recordContentSource>Wilson County Archives</mods:recordContentSource>
<mods:recordCreationDate encoding="w3cdtf">2008-08-18</mods:recordCreationDate>
<mods:languageOfCataloging>
<mods:languageTerm type="code" authority="iso639-2b">eng</mods:languageTerm>
</mods:languageOfCataloging>
</mods:recordInfo>
<mods:accessCondition type="useAndReproduction">http://idserver.utk.edu/?id=200600000001200</mods:accessCondition>
</mods:mods>\n\n\n