<?xml version="1.0" encoding="UTF-8"  ?>
<mods:mods xmlns:mods="http://www.loc.gov/mods/v3" 
 xmlns:xlink="http://www.w3.org/1999/xlink" 
 xmlns="http://www.loc.gov/mods/v3" 
 xmlns:xsi="http://www.w3.org/2001/XMLSchema-instance" 
 xsi:schemaLocation="http://www.loc.gov/mods/v3 
 http://www.loc.gov/standards/mods/v3/mods-3-2.xsd" ID="MODS" version="3.2"><!-- Volunteer Voices MODS profile 
 released 14 December 2006 by Melanie Feltner-Reichert -->
<!-- Volunteer Voices Workbook 
 version 1.0 released 6 February 2007 by Christine Haygood Deane  -->
<!-- Content Contributor:  Gregory Hall -->  
<!-- Project:  Volunteer Voices -->  
<!-- Record Creation Date:  Tue Nov 27 14:36:35 EST 2007 -->  
<!-- BATCH_ID: 071205 -->
<!-- FILENAME: C:\Scan\00\xml\0014_000062_000267_0000.xml  -->  
<!-- NUMBER_OF_CONSTITUENT_FILES: 1: -->  
<!-- Reload: none --> 
<!-- PAGE VALIDATION :1:1:1:1:1:1:1: -->  
<mods:titleInfo>
<mods:title>Electrical Machines Exhibit</mods:title>
</mods:titleInfo>
<mods:name  type="personal">
<mods:namePart type="family">Poland</mods:namePart>
<mods:namePart type="given">Clifford Hoyte</mods:namePart>
<mods:role>
<mods:roleTerm authority="marcrelator">Photographer</mods:roleTerm>
</mods:role>
</mods:name>
<mods:originInfo>
<mods:dateCreated  keyDate="yes"  encoding="w3cdtf">1917</mods:dateCreated>
</mods:originInfo>
<mods:language>
<mods:languageTerm type="code" authority="iso639-2b">eng</mods:languageTerm>
</mods:language>
<mods:typeOfResource>still image</mods:typeOfResource>
<mods:genre authority="aat" >black-and-white-photographs</mods:genre>
<mods:physicalDescription>
<mods:digitalOrigin>reformatted digital</mods:digitalOrigin>
<mods:internetMediaType>image/jpeg</mods:internetMediaType>
<mods:extent>1 digital image; 1 photograph</mods:extent>
</mods:physicalDescription>
<mods:abstract>An exhibit at the 1917 Tri-State Fair in Memphis, Tennessee.</mods:abstract>
<mods:subject authority="lcsh">
<mods:topic>Appliances 1910-1920</mods:topic>
<mods:topic>Fairs</mods:topic>
<mods:geographic>Memphis (Tenn.) -- Commerce</mods:geographic>
</mods:subject>
<mods:subject authority="vv">
<mods:temporal>A.7</mods:temporal>
<mods:topic>D.22</mods:topic>
<mods:topic>D.19</mods:topic>
</mods:subject>
<mods:relatedItem type="constituent">
<mods:identifier type="local">0014_000062_000267_0001</mods:identifier>
</mods:relatedItem >
<mods:identifier type="uri"></mods:identifier>
<mods:location>
<mods:physicalLocation type="repository">Memphis Public Library</mods:physicalLocation>
<mods:physicalLocation type="city">Memphis</mods:physicalLocation>
<mods:physicalLocation type="state">Tennessee</mods:physicalLocation>
<mods:physicalLocation type="county">C.79</mods:physicalLocation>
<mods:physicalLocation type="collection">Memphis and Shelby County Room Photographic Collection</mods:physicalLocation>
<mods:url>Jody</mods:url>
</mods:location>
<mods:recordInfo>
<mods:recordContentSource>University of Tennessee Special Collections Library</mods:recordContentSource>
<mods:recordCreationDate encoding="w3cdtf">2007-11-27</mods:recordCreationDate>
<mods:languageOfCataloging>
<mods:languageTerm type="code" authority="iso639-2b">eng</mods:languageTerm>
</mods:languageOfCataloging>
</mods:recordInfo>
<mods:accessCondition type="useAndReproduction">http://idserver.utk.edu/?id=200600000001200</mods:accessCondition>
</mods:mods>


